deckard/__init__.py
deckard/main.py
deckard/patterns/__init__ .py
deckard/patterns/pl.py
deckard/patterns/standard.py
deckard-0.1.0.dist-info/LICENSE
deckard-0.1.0.dist-info/METADATA
deckard-0.1.0.dist-info/WHEEL
deckard-0.1.0.dist-info/RECORD
