Metadata-Version: 2.3
Name: deckard
Version: 0.1.0
Summary: Extract structured data from unstructured text — no AI, just regular expressions. 🔍
License: MIT
Keywords: regex,data-extraction,regular-expression
Author: SpaceShaman
Author-email: spaceshaman@tuta.io
Requires-Python: >=3.10,<4.0
Classifier: License :: OSI Approved :: MIT License
Classifier: Programming Language :: Python :: 3
Classifier: Programming Language :: Python :: 3.10
Classifier: Programming Language :: Python :: 3.11
Classifier: Programming Language :: Python :: 3.12
Classifier: Programming Language :: Python :: 3.13
Requires-Dist: regex (>=2025,<2026)
Project-URL: Documentation, https://github.com/SpaceShaman/deckard
Project-URL: Homepage, https://github.com/SpaceShaman/deckard
Project-URL: Repository, https://github.com/SpaceShaman/deckard
